cupid/__init__.py
cupid/backend.py
cupid/cdfdicts.py
cupid/cxdh.py
cupid/dosi.py
cupid/mags.py
cupid/plotutils.py
cupid/xray.py
cupidsat-1.1.5.dist-info/LICENSE
cupidsat-1.1.5.dist-info/METADATA
cupidsat-1.1.5.dist-info/WHEEL
cupidsat-1.1.5.dist-info/top_level.txt
cupidsat-1.1.5.dist-info/RECORD
